srec/__init__.py
srec-1.1.dist-info/METADATA
srec-1.1.dist-info/WHEEL
srec-1.1.dist-info/licenses/LICENSE
srec-1.1.dist-info/RECORD
