Metadata-Version: 2.1
Name: srec
Version: 1.1
Summary: A simple module to calculate the time required for leveling up in Honkai: Star rail.
Project-URL: Homepage, https://github.com/Trrrrw/srec
Project-URL: Bug Tracker, https://github.com/Trrrrw/srec/issues
Author-email: Trrrrw <wzhhenry@qq.com>
License-File: LICENSE
Classifier: License :: OSI Approved :: MIT License
Classifier: Operating System :: OS Independent
Classifier: Programming Language :: Python :: 3
Requires-Python: >=3.7
